crypto_cookie/__init__.py
crypto_cookie/auth_tkt.py
crypto_cookie/encoding.py
crypto_cookie/encryption.py
crypto_cookie/exceptions.py
crypto_cookie/signature.py
crypto_cookie/test/__init__.py
crypto_cookie/test/test_encrypt.py
crypto_cookie-0.3.1.dist-info/METADATA
crypto_cookie-0.3.1.dist-info/RECORD
crypto_cookie-0.3.1.dist-info/WHEEL
crypto_cookie-0.3.1.dist-info/top_level.txt
