Metadata-Version: 2.1
Name: crypto-cookie
Version: 0.3.1
Summary: Package to encrypt and sign cookies
Home-page: https://github.com/cedadev/crypto-cookie
Author: Philip Kershaw
Author-email: Philip.Kershaw@stfc.ac.uk
Maintainer: Philip Kershaw
Maintainer-email: Philip.Kershaw@stfc.ac.uk
License: BSD - See LICENCE file for details
Platform: UNKNOWN
Classifier: Development Status :: 4 - Beta
Classifier: License :: OSI Approved :: BSD License
Classifier: Operating System :: OS Independent
Classifier: Programming Language :: Python :: 2
Classifier: Programming Language :: Python :: 2.7
Classifier: Programming Language :: Python :: 3
Classifier: Programming Language :: Python :: 3.6
Requires-Dist: cryptography
